LICENSE
MANIFEST.in
README.md
README.rst
setup.py
keras_tweaks/__init__.py
keras_tweaks/dense_sparse_matmul.py
keras_tweaks/get_sparsity_pattern.py
keras_tweaks/idseqs_to_mask.py
keras_tweaks/normalizations.py
keras_tweaks/sparsity_analysis.py
keras_tweaks.egg-info/PKG-INFO
keras_tweaks.egg-info/SOURCES.txt
keras_tweaks.egg-info/dependency_links.txt
keras_tweaks.egg-info/requires.txt
keras_tweaks.egg-info/top_level.txt
keras_tweaks.egg-info/zip-safe
test/__init__.py
test/test_dense_sparse_matmul.py
test/test_idseqs_to_mask.py
test/test_normalizations.py
test/test_sparsity_analysis.py
test/test_sparsity_pattern.py