Metadata-Version: 2.1
Name: keras-tweaks
Version: 0.4.1
Summary: Utility functions for Keras/Tensorflow2.
Home-page: http://github.com/ulf1/keras-tweaks
Author: Ulf Hamster
Author-email: 554c46@gmail.com
License: Apache License 2.0
Platform: UNKNOWN
Requires-Python: >=3.7
License-File: LICENSE
